cpp/verilog/Work/CPU_Project/src/defines.vh
// ===========指令Opcode定义===========
`define OP_RTYPE 6'b00_0000   // R-Type指令的操作码
`define OP_ADDI  6'b00_1000
`define OP_ADDIU 6'b00_1001
`define OP_ANDI  6'b00_1100
`define OP_ORI   6'b00_1101
`define OP_XORI  6'b00_1110
`define OP_LUI   6'b00_1111
`define OP_LW    6'b10_0011
`define OP_SW    6'b10_1011
`define OP_BEQ   6'b00_0100
`define OP_BNE   6'b00_0101
`define OP_SLTI  6'b00_1010
`define OP_SLTIU 6'b00_1011
`define OP_J     6'b00_0010
`define OP_JAL   6'b00_0011

// =======R-Type指令的Funct字段定义=======

`define FUNCT_ADD  6'b10_0000
`define FUNCT_ADDU 6'b10_0001
`define FUNCT_SUB  6'b10_0010
`define FUNCT_SUBU 6'b10_0011
`define FUNCT_AND  6'b10_0100
`define FUNCT_OR   6'b10_0101
`define FUNCT_XOR  6'b10_0110
`define FUNCT_NOR  6'b10_0111
`define FUNCT_SLT  6'b10_1010
`define FUNCT_SLTU 6'b10_1011
`define FUNCT_SLL  6'b00_0000
`define FUNCT_SRL  6'b00_0010
`define FUNCT_SRA  6'b00_0011
`define FUNCT_SLLV 6'b00_0100
`define FUNCT_SRLV 6'b00_0110
`define FUNCT_SRAV 6'b00_0111
`define FUNCT_JR   6'b00_1000

// ==========ALU操作控制信号定义==========

`define ALU_ADD  4'b0000
`define ALU_SUB  4'b0001
`define ALU_AND  4'b0010
`define ALU_OR   4'b0011
`define ALU_XOR  4'b0100 // 异或运算
`define ALU_NOR  4'b0101 // 或非运算
`define ALU_SLT  4'b0110 // 有符号比较
`define ALU_SLTU 4'b0111 // 无符号比较
`define ALU_SLL  4'b1000 // 逻辑左移
`define ALU_SRL  4'b1001 // 逻辑右移
`define ALU_SRA  4'b1010 // 算术右移
`define ALU_LUI  4'b1011 // 用于LUI指令

// ==========程序计数器初始地址==========

`define PC_INIT 32'h0000_0000

// ========指令存储器大小相关定义=========

`define IMEM_SIZE 1024        // 指令存储器大小（字数）
`define IMEM_ADDR_WIDTH 12    // 指令存储器地址宽度

// ========数据存储器操作宽度定义=========

`define MEM_WIDTH_BYTE   2'b00
`define MEM_WIDTH_HALF   2'b01
`define MEM_WIDTH_WORD   2'b10

/*
// ========数据存储器操作类型定义=========

`define MEM_OP_LBYTE        3'b000    // 有符号字节加载
`define MEM_OP_LHALF        3'b001    // 有符号半字加载
`define MEM_OP_LWORD        3'b010    // 字加载
`define MEM_OP_LBYTEU       3'b100    // 无符号字节加载
`define MEM_OP_LHALFU       3'b101    // 无符号半字加载
*/

cpp/verilog/Work/CPU_Project/src/core/control_unit.v
`timescale 1ns/1ps
`include "E:\Vivado\Work\CPU_Project\src\defines.vh"

module control_unit(
    input wire [5:0] opcode,             // 指令操作码
    input wire [5:0] funct,              // 功能字段（用于R型指令）
    output reg reg_write_en,             // 寄存器写使能
    output reg mem_to_reg_sel,           // 内存到寄存器选择
    output reg mem_write_en,             // 内存写使能
    output reg mem_read_en,              // 内存读使能
    output reg branch_en,                // 分支指令使能
    output reg alu_src_sel,              // ALU源选择（寄存器/立即数）
    output reg reg_dst_sel,              // 寄存器目标选择
    output reg [1:0] alu_op,             // ALU操作类型指示
    output reg jump_en,                  // 跳转指令使能
    output reg jal_sel,                  // JAL指令选择
    output reg jr_sel                    // JR指令选择
);

    wire is_rtype;
    assign is_rtype = (opcode == `OP_RTYPE);
    
    always @(*) begin
        reg_write_en = 1'b0;
        mem_to_reg_sel = 1'b0;
        mem_write_en = 1'b0;
        mem_read_en = 1'b0;
        branch_en = 1'b0;
        alu_src_sel = 1'b0;
        reg_dst_sel = 1'b0;
        alu_op = 2'b00;
        jump_en = 1'b0;
        jal_sel = 1'b0;
        jr_sel = 1'b0;
    
        case(opcode)
            `OP_RTYPE: begin // R-Type 指令
                reg_write_en = 1'b1;
                reg_dst_sel = 1'b1;
                alu_src_sel = 1'b0;
                alu_op = 2'b10; // 表示R-type指令，需要ALU控制单元进一步解码
    
                // JR指令特殊处理
                if (funct == `FUNCT_JR) begin
                    reg_write_en = 1'b0;    // JR不写寄存器
                    jump_en = 1'b1;         // 需要跳转
                    jr_sel = 1'b1;          // 是JR指令
                end
            end
    
            // I-Type 指令
    
            // 立即数运算指令 (I-Type) 这些指令将一个寄存器中的数据与一个立即数（编码在指令中的常数）进行运算。
                // ALU 操作：这些指令同样需要 ALU 执行 ADD, AND, OR, SLT 等操作。区别在于第二个操作数来自指令中的立即数字段，需要经过符号扩展或零扩展单元处理后，再送给 ALU。
            `OP_ADDI,`OP_ADDIU: begin   //	addi $1, $2, 100	加立即数	$1 = $2 + 100 (有符号，检查溢出)        addiu $1, $2, 100	加立即数	$1 = $2 + 100 (无符号，不检查溢出)
                reg_write_en = 1'b1;
                alu_src_sel = 1'b1;
                alu_op = 2'b00; // 加法操作
            end
    
            `OP_ANDI: begin   // andi $1, $2, 0xFF	与立即数	$1 = $2 & 0xFF (0扩展立即数)
                reg_write_en = 1'b1;
                alu_src_sel = 1'b1;
                alu_op = 2'b11; // 需要特殊处理
            end
    
            `OP_ORI: begin    // ori $1, $2, 0xFF	或立即数	$1 = $2 | 0xFF
                reg_write_en = 1'b1;
                alu_src_sel = 1'b1;
                alu_op = 2'b11; // 需要特殊处理
            end
    
            `OP_XORI: begin   // xori $1, $2, 0xFF	异或立即数	$1 = $2 ^ 0xFF (0扩展立即数)
                reg_write_en = 1'b1;
                alu_src_sel = 1'b1;
                alu_op = 2'b11; // 需要特殊处理
            end
    
            `OP_SLTI: begin   // slti $1, $2, 100	小于立即数置位	if ($2 < 100) $1=1 else $1=0 (有符号比较)
                reg_write_en = 1'b1;
                alu_src_sel = 1'b1;
                alu_op = 2'b11; // 需要特殊处理
            end
    
            `OP_SLTIU: begin  // sltiu $1, $2, 100	小于立即数置位	if ($2 < 100) $1=1 else $1=0 (无符号比较
                reg_write_en = 1'b1;
                alu_src_sel = 1'b1;
                alu_op = 2'b11; // 需要特殊处理
            end
    
            `OP_LUI: begin    // lui $1, 0x1234	加载高位立即数	$1 = 0x1234 << 16 (将16位立即数放到高16位，低16位为0)
                reg_write_en = 1'b1;
                alu_src_sel = 1'b1;
                alu_op = 2'b11; // 需要特殊处理
            end
    
            // 数据传输指令 (I-Type) - 回答你的核心问题 
                // ALU 在这两条指令中的作用：
                //     地址计算：ALU 的核心任务是执行 $2 + 100。这里的 100 是指令中的16位偏移量，需要先进行符号扩展成32位，再和 $2 的值一起送入 ALU 执行 ADD 操作。
                //     结果：ALU 输出的32位结果就是访问内存的有效地址。
                //     内存访问：对于 lw，控制单元会使用这个地址从数据内存中读取数据，然后通过另一个多路选择器写回到寄存器 $1。
                //              对于 sw，控制单元会使用这个地址，将寄存器 $1 的值写入数据内存。
                // 所以，lw/sw 本身不是 ALU 操作，但它们依赖 ALU 来完成最关键的地址计算工作。
            `OP_LW: begin     // lw $1, 100($2)	  从内存加载字	 $1 = Memory[$2 + 100]
                reg_write_en = 1'b1;
                mem_to_reg_sel = 1'b1;
                alu_src_sel = 1'b1;
                mem_read_en = 1'b1;
                alu_op = 2'b00; // 加法操作
            end
    
            `OP_SW: begin     // sw $1, 100($2)	  向内存存储字	 Memory[$2 + 100] = $1
                alu_src_sel = 1'b1;
                mem_write_en = 1'b1;
                alu_op = 2'b00; // 加法操作
            end
    
            // 分支指令 (I-Type) 根据条件决定是否改变程序执行流程（跳转）
                // ALU 的作用：ALU 需要执行 SUB 操作来计算 $1 - $2，并产生 zero 标志位。控制单元根据 zero 标志位的结果来决定是否跳转。同时，跳转地址的计算 PC + 4 + (offset << 2) 也可能需要另一个加法器（或复用 ALU）来完成。
            `OP_BEQ: begin  // beq $1, $2, label    相等则分支     if ($1 == $2) jump to label
                branch_en = 1'b1;
                alu_op = 2'b01; // 减法操作
            end
    
            `OP_BNE: begin  // bne $1, $2, label    不等则分支     if ($1 != $2) jump to label
                branch_en = 1'b1;
                alu_op = 2'b01; // 减法操作
            end
    
            // J-Type 指令
                // ALU 的作用：ALU 需要执行 SUB 操作来计算 $1 - $2，并产生 zero 标志位。控制单元根据 zero 标志位的结果来决定是否跳转。同时，跳转地址的计算 PC + 4 + (offset << 2) 也可能需要另一个加法器（或复用 ALU）来完成。
            //跳转指令 (J-Type) 无条件改变程序执行流程。
            `OP_J: begin    // j label	跳转	直接跳转到 label 处执行
                jump_en = 1'b1;
            end
    
            `OP_JAL: begin  // jal func	跳转并链接	跳转到 func，同时将返回地址(PC+4)存入 $ra($31)
                jump_en = 1'b1;
                jal_sel = 1'b1;
                reg_write_en = 1'b1;
            end
    
            default: begin  
                reg_write_en = 1'b0;
                mem_to_reg_sel = 1'b0;
                mem_write_en = 1'b0;
                mem_read_en = 1'b0;
                branch_en = 1'b0;
                alu_src_sel = 1'b0;
                reg_dst_sel = 1'b0;
                alu_op = 2'b00;
                jump_en = 1'b0;
                jal_sel = 1'b0;
                jr_sel = 1'b0;
            end
        endcase
    end        
endmodule

verilog/Work/CPU_Project/testbench/unit_tests/control_unit_tb.v
`timescale 1ns/1ps
`include "E:/Vivado/Work/CPU_Project/src/defines.vh"

module control_unit_tb;

    // 输入
    reg [5:0] opcode;
    reg [5:0] funct;
    
    // 输出
    wire reg_write_en;
    wire mem_to_reg_sel;
    wire mem_write_en;
    wire mem_read_en;
    wire branch_en;
    wire alu_src_sel;
    wire reg_dst_sel;
    wire [1:0] alu_op;
    wire jump_en;
    wire jal_sel;
    wire jr_sel;
    
    // 实例化被测试单元
    control_unit uut (
        .opcode(opcode),
        .funct(funct),
        .reg_write_en(reg_write_en),
        .mem_to_reg_sel(mem_to_reg_sel),
        .mem_write_en(mem_write_en),
        .mem_read_en(mem_read_en),
        .branch_en(branch_en),
        .alu_src_sel(alu_src_sel),
        .reg_dst_sel(reg_dst_sel),
        .alu_op(alu_op),
        .jump_en(jump_en),
        .jal_sel(jal_sel),
        .jr_sel(jr_sel)
    );
    
    // 测试过程
    initial begin
        // 打开VCD文件用于波形查看
        $dumpfile("control_unit_tb.vcd");
        $dumpvars(0, control_unit_tb);
        
        // 初始化输入
        opcode = 0;
        funct = 0;
        
        // 监视输出 - 使用英文标签避免乱码
        $monitor("Time=%0t op=%h fn=%h | rwe=%b m2r=%b mwe=%b mre=%b br=%b as=%b rd=%b aop=%b j=%b js=%b jrs=%b", 
                 $time, opcode, funct, reg_write_en, mem_to_reg_sel, mem_write_en, mem_read_en, 
                 branch_en, alu_src_sel, reg_dst_sel, alu_op, jump_en, jal_sel, jr_sel);
        
        // 测试R型指令-ADD
        #10;
        opcode = `OP_RTYPE;
        funct = `FUNCT_ADD;
        
        // 测试R型指令-SUB
        #10;
        funct = `FUNCT_SUB;
        
        // 测试R型指令-AND
        #10;
        funct = `FUNCT_AND;
        
        // 测试R型指令-JR
        #10;
        funct = `FUNCT_JR;
        
        // 测试LW指令
        #10;
        opcode = `OP_LW;
        funct = 0;
        
        // 测试SW指令
        #10;
        opcode = `OP_SW;
        
        // 测试ADDI指令
        #10;
        opcode = `OP_ADDI;
        
        // 测试ANDI指令
        #10;
        opcode = `OP_ANDI;
        
        // 测试BEQ指令
        #10;
        opcode = `OP_BEQ;
        
        // 测试J指令
        #10;
        opcode = `OP_J;
        
        // 测试JAL指令
        #10;
        opcode = `OP_JAL;
        
        // 测试LUI指令
        #10;
        opcode = `OP_LUI;
        
        // 结束测试
        #10;
        $finish;
    end

endmodule

verilog/Work/CPU_Project/CPU_Project.sim/sim_1/behav/xsim/control_unit_tb.vcd
$date
   Thu Sep 11 12:27:37 2025
$end

$version
  2025.1.0
  $dumpfile ("control_unit_tb.vcd") 
$end

$timescale
  1ps
$end

$scope module control_unit_tb $end
$var reg 6 ! opcode [5:0] $end
$var reg 6 " funct [5:0] $end
$var wire 1 # reg_write_en $end
$var wire 1 $ mem_to_reg_sel $end
$var wire 1 % mem_write_en $end
$var wire 1 & mem_read_en $end
$var wire 1 ' branch_en $end
$var wire 1 ( alu_src_sel $end
$var wire 1 ) reg_dst_sel $end
$var wire 2 * alu_op [1:0] $end
$var wire 1 + jump_en $end
$var wire 1 , jal_sel $end
$var wire 1 - jr_sel $end
$scope module uut $end
$var wire 6 . opcode [5:0] $end
$var wire 6 / funct [5:0] $end
$var reg 1 0 reg_write_en $end
$var reg 1 1 mem_to_reg_sel $end
$var reg 1 2 mem_write_en $end
$var reg 1 3 mem_read_en $end
$var reg 1 4 branch_en $end
$var reg 1 5 alu_src_sel $end
$var reg 1 6 reg_dst_sel $end
$var reg 2 7 alu_op [1:0] $end
$var reg 1 8 jump_en $end
$var reg 1 9 jal_sel $end
$var reg 1 : jr_sel $end
$var wire 1 ; is_rtype $end
$upscope $end
$upscope $end
$enddefinitions $end

#0
$dumpvars
b0 !
b0 "
1#
0$
0%
0&
0'
0(
1)
b10 *
0+
0,
0-
b0 .
b0 /
10
01
02
03
04
05
16
b10 7
08
09
0:
1;
$end

#10000
b100000 "
b100000 /
10
16
b10 7

#20000
b100010 "
b100010 /
10
16
b10 7

#30000
b100100 "
b100100 /
10
16
b10 7

#40000
b1000 "
0#
1+
1-
b1000 /
00
16
b10 7
18
1:

#50000
b100011 !
b0 "
1#
1$
1&
1(
0)
b0 *
0+
0-
b100011 .
b0 /
10
11
13
15
06
b0 7
08
0:
0;

#60000
b101011 !
0#
0$
1%
0&
b101011 .
00
01
12
03
15

#70000
b1000 !
1#
0%
b1000 .
10
02
15

#80000
b1100 !
b11 *
b1100 .
10
15
b11 7

#90000
b100 !
0#
1'
0(
b1 *
b100 .
00
14
05
b1 7

#100000
b10 !
0'
b0 *
1+
b10 .
04
b0 7
18

#110000
b11 !
1#
1,
b11 .
10
18
19

#120000
b1111 !
1(
b11 *
0+
0,
b1111 .
10
15
b11 7
08
09
