cpp/verilog/Work/CPU_Project/src/core/alu.v
`timescale 1ns/1ps

`include "E:\Vivado\Work\CPU_Project\src\defines.vh"

module alu (
    input [31:0] a,
    input [31:0] b,
    input [3:0] alu_control,
    output reg [31:0] result,
    output zero
);
    
    always @(*) begin
        case(alu_control)
            `ALU_ADD : result = a + b;
            `ALU_SUB : result = a - b;
            `ALU_AND : result = a & b;
            `ALU_OR  : result = a | b;
            `ALU_XOR : result = a ^ b;
            `ALU_NOR : result = ~(a | b);
            `ALU_SLT : result = ($signed(a) < $signed(b)) ? 32'd1 : 32'd0;
            `ALU_SLTU: result = (a < b) ? 32'd1 : 32'd0;
            `ALU_SLL : result = b << a[4:0];
            `ALU_SRL : result = b >> a[4:0];
            `ALU_SRA : result = $signed(b) >>> a[4:0];
            `ALU_LUI : result = {b[15:0], 16'b0};
            default  : result = 32'bx;
        endcase
    end

    assign zero = (result == 32'b0);
endmodule

verilog/Work/CPU_Project/sim/unit_tests/alu_tb.v
`timescale 1ns/1ps

`include "E:\Vivado\Work\CPU_Project\src\defines.vh"

module alu_tb;
    // Define signals
    reg [31:0] a, b;
    reg [3:0] alu_control;
    wire [31:0] result;
    wire zero;
    
    // Instantiate the ALU under test
    alu uut (
        .a(a),
        .b(b),
        .alu_control(alu_control),
        .result(result),
        .zero(zero)
    );
    
    integer test_count;
    integer passed_tests;
    
    // Test task: Check results and report
    task check_test;
        input [31:0] expected_result;
        input expected_zero;
        input [100:0] test_name;
        begin
            test_count = test_count + 1;
            #10; // Wait for stability
            
            if (result === expected_result && zero === expected_zero) begin
                $display("PASS");
                passed_tests = passed_tests + 1;
            end else begin
                $display("FAIL");
                $display("   Expected: result=0x%h, zero=%b", expected_result, expected_zero);
                $display("   Got:      result=0x%h, zero=%b", result, zero);
            end
        end
    endtask
    
    // Test process
    initial begin
        // Initialize
        test_count = 0;
        passed_tests = 0;
        a = 0;
        b = 0;
        alu_control = 0;
        
        #10
        $display("Starting ALU testbench...");
        $display("----------------------------------------");
        
        // Test addition
        alu_control = `ALU_ADD;
        a = 32'h00000005;
        b = 32'h00000003;
        check_test(32'h00000008, 0, "ADD");
        
        a = 32'hFFFFFFFF;
        b = 32'h00000001;
        check_test(32'h00000000, 1, "ADD");
        
        // Test subtraction
        alu_control = `ALU_SUB;
        a = 32'h0000000A;
        b = 32'h00000003;
        check_test(32'h00000007, 0, "SUB");
        
        a = 32'h00000005;
        b = 32'h0000000A;
        check_test(32'hFFFFFFFB, 0, "SUB");
        
        // Test AND operation
        alu_control = `ALU_AND;
        a = 32'hF0F0F0F0;
        b = 32'h12345678;
        check_test(32'h10305070, 0, "AND");
        
        // Test OR operation
        alu_control = `ALU_OR;
        a = 32'hF0F0F0F0;
        b = 32'h0F0F0F0F;
        check_test(32'hFFFFFFFF, 0, "OR");
        
        // Test XOR operation
        alu_control = `ALU_XOR;
        a = 32'hAAAAAAAA;
        b = 32'h55555555;
        check_test(32'hFFFFFFFF, 0, "XOR");
        
        // Test NOR operation
        alu_control = `ALU_NOR;
        a = 32'h12345678;
        b = 32'h0000FFFF;
        check_test(~(32'h12345678 | 32'h0000FFFF), 0, "NOR");
        
        // Test signed comparison
        alu_control = `ALU_SLT;
        a = 32'hFFFFFFFE; // -2
        b = 32'h00000001; // 1
        check_test(32'h00000001, 0, "SLT");
        
        a = 32'h00000005; // 5
        b = 32'h00000003; // 3
        check_test(32'h00000000, 1, "SLT");
        
        // Test unsigned comparison
        alu_control = `ALU_SLTU;
        a = 32'hFFFFFFFE; // 4294967294
        b = 32'h00000001; // 1
        check_test(32'h00000000, 1, "SLTU");
        
        a = 32'h00000005; // 5
        b = 32'h0000000A; // 10
        check_test(32'h00000001, 0, "SLTU");
        
        // Test logical left shift
        alu_control = `ALU_SLL;
        a = 32'h00000004; // Shift amount
        b = 32'h0000000F; // Number to shift
        check_test(32'h000000F0, 0, "SLL");
        
        // Test logical right shift
        alu_control = `ALU_SRL;
        a = 32'h00000004; // Shift amount
        b = 32'hF000000F; // Number to shift
        check_test(32'h0F000000, 0, "SRL");
        
        // Test arithmetic right shift
        alu_control = `ALU_SRA;
        a = 32'h00000004; // Shift amount
        b = 32'hF000000F; // Number to shift (negative number)
        check_test(32'hFF000000, 0, "SRA");
        
        // Test LUI instruction
        alu_control = `ALU_LUI;
        b = 32'h00001234; // Low 16-bit immediate
        check_test(32'h12340000, 0, "LUI");
        
        // Test zero flag
        alu_control = `ALU_ADD;
        a = 32'h00000000;
        b = 32'h00000000;
        check_test(32'h00000000, 1, "Zero flag");
        
        // Test boundary case
        alu_control = `ALU_ADD;
        a = 32'h7FFFFFFF; // Maximum positive number
        b = 32'h00000001; // Add 1
        check_test(32'h80000000, 0, "Boundary");
        
        // Test undefined opcode (should return x)
        alu_control = 4'b1111; // Undefined opcode
        a = 32'h12345678;
        b = 32'h87654321;
        #10;
        if (result === 32'bx) begin
            $display("PASS: Undefined opcode returns x");
            passed_tests = passed_tests + 1;
        end else begin
            $display("FAIL: Undefined opcode should return x");
        end
        test_count = test_count + 1;
        
        // Test summary
        #10;
        $display("----------------------------------------");
        $display("Test Summary: %0d/%0d tests passed", passed_tests, test_count);
        
        if (passed_tests == test_count) begin
            $display("All tests passed!");
        end else begin
            $display("Some tests failed!");
        end
        
        $finish;
    end
    
    // Generate waveform file (for debugging)
    initial begin
        $dumpfile("alu_wave.vcd");
        $dumpvars(0, alu_tb);
    end
endmodule

cpp/verilog/Work/CPU_Project/CPU_Project.sim/sim_1/behav/xsim/alu_wave.vcd
$date
   Sat Sep 20 12:22:53 2025
$end

$version
  2025.1.0
  $dumpfile ("alu_wave.vcd") 
$end

$timescale
  1ps
$end

$scope module alu_tb $end
$var reg 32 ! a [31:0] $end
$var reg 32 " b [31:0] $end
$var reg 4 # alu_control [3:0] $end
$var wire 32 $ result [31:0] $end
$var wire 1 % zero $end
$var integer 32 & test_count [31:0] $end
$var integer 32 ' passed_tests [31:0] $end
$scope module uut $end
$var wire 32 ( a [31:0] $end
$var wire 32 ) b [31:0] $end
$var wire 4 * alu_control [3:0] $end
$var reg 32 + result [31:0] $end
$var wire 1 % zero $end
$upscope $end
$scope task check_test $end
$var reg 32 , expected_result [31:0] $end
$var reg 1 - expected_zero $end
$var reg 101 . test_name [100:0] $end
$upscope $end
$upscope $end
$enddefinitions $end

#0
$dumpvars
b0 !
b0 "
b0 #
b0 $
1%
b0 &
b0 '
b0 (
b0 )
b0 *
b0 +
bx ,
x-
bx .
$end

#10000
b101 !
b11 "
b1000 $
0%
b1 &
b101 (
b11 )
b1000 +
b1000 ,
0-
b10000010100010001000100 .

#20000
b11111111111111111111111111111111 !
b1 "
b0 $
1%
b10 &
b1 '
b11111111111111111111111111111111 (
b1 )
b0 +
b0 ,
1-

#30000
b1010 !
b11 "
b1 #
b111 $
0%
b11 &
b10 '
b1010 (
b11 )
b1 *
b111 +
b111 ,
0-
b10100110101010101000010 .

#40000
b101 !
b1010 "
b11111111111111111111111111111011 $
b100 &
b11 '
b101 (
b1010 )
b11111111111111111111111111111011 +
b11111111111111111111111111111011 ,

#50000
b11110000111100001111000011110000 !
b10010001101000101011001111000 "
b10 #
b10000001100000101000001110000 $
b101 &
b100 '
b11110000111100001111000011110000 (
b10010001101000101011001111000 )
b10 *
b10000001100000101000001110000 +
b10000001100000101000001110000 ,
b10000010100111001000100 .

#60000
b1111000011110000111100001111 "
b11 #
b11111111111111111111111111111111 $
b110 &
b101 '
b1111000011110000111100001111 )
b11 *
b11111111111111111111111111111111 +
b11111111111111111111111111111111 ,
b100111101010010 .

#70000
b10101010101010101010101010101010 !
b1010101010101010101010101010101 "
b100 #
b111 &
b110 '
b10101010101010101010101010101010 (
b1010101010101010101010101010101 )
b100 *
b10110000100111101010010 .

#80000
b10010001101000101011001111000 !
b1111111111111111 "
b101 #
b11101101110010110000000000000000 $
b1000 &
b111 '
b10010001101000101011001111000 (
b1111111111111111 )
b101 *
b11101101110010110000000000000000 +
b11101101110010110000000000000000 ,
b10011100100111101010010 .

#90000
b11111111111111111111111111111110 !
b1 "
b110 #
b1 $
b1001 &
b1000 '
b11111111111111111111111111111110 (
b1 )
b110 *
b1 +
b1 ,
b10100110100110001010100 .

#100000
b101 !
b11 "
b0 $
1%
b1010 &
b1001 '
b101 (
b11 )
b0 +
b0 ,
1-

#110000
b11111111111111111111111111111110 !
b1 "
b111 #
b1011 &
b1010 '
b11111111111111111111111111111110 (
b1 )
b111 *
b1010011010011000101010001010101 .

#120000
b101 !
b1010 "
b1 $
0%
b1100 &
b1011 '
b101 (
b1010 )
b1 +
b1 ,
0-

#130000
b100 !
b1111 "
b1000 #
b11110000 $
b1101 &
b1100 '
b100 (
b1111 )
b1000 *
b11110000 +
b11110000 ,
b10100110100110001001100 .

#140000
b11110000000000000000000000001111 "
b1001 #
b1111000000000000000000000000 $
b1110 &
b1101 '
b11110000000000000000000000001111 )
b1001 *
b1111000000000000000000000000 +
b1111000000000000000000000000 ,
b10100110101001001001100 .

#150000
b1010 #
b11111111000000000000000000000000 $
b1111 &
b1110 '
b1010 *
b11111111000000000000000000000000 +
b11111111000000000000000000000000 ,
b10100110101001001000001 .

#160000
b1001000110100 "
b1011 #
b10010001101000000000000000000 $
b10000 &
b1111 '
b1001000110100 )
b1011 *
b10010001101000000000000000000 +
b10010001101000000000000000000 ,
b10011000101010101001001 .

#170000
b0 !
b0 "
b0 #
b0 $
1%
b10001 &
b10000 '
b0 (
b0 )
b0 *
b0 +
b0 ,
1-
b10110100110010101110010011011110010000001100110011011000110000101100111 .

#180000
b1111111111111111111111111111111 !
b1 "
b10000000000000000000000000000000 $
0%
b10010 &
b10001 '
b1111111111111111111111111111111 (
b1 )
b10000000000000000000000000000000 +
b10000000000000000000000000000000 ,
0-
b100001001101111011101010110111001100100011000010111001001111001 .

#190000
b10010001101000101011001111000 !
b10000111011001010100001100100001 "
b1111 #
bx $
x%
b10010 '
b10010001101000101011001111000 (
b10000111011001010100001100100001 )
b1111 *
bx +

#200000
b10011 &
b10011 '
