verilog/Work/CPU_Project/src/core/register_file.v
`timescale 1ns/1ps

module register_file(
    input wire clk,
    input wire rst_n,
    input wire write_enable,
    input wire [4:0] read_addr1,
    input wire [4:0] read_addr2,
    input wire [4:0] write_addr,
    input wire [31:0] write_data,
    output wire [31:0] read_data1,
    output wire [31:0] read_data2
);

    reg [31:0] register_bank [0:31]; // 32个32位寄存器

    // 异步读：指读取操作不需要时钟信号触发，一旦地址输入发生变化，经过一定的组合逻辑延迟后，数据就会立即输出。
    assign read_data1 = (read_addr1 == 5'b0) ? 32'b0 : register_bank[read_addr1];
    assign read_data2 = (read_addr2 == 5'b0) ? 32'b0 : register_bank[read_addr2];

    // 同步写：指写入操作需要时钟信号触发，只有在时钟的有效边沿（通常是上升沿）到来时，并且满足特定条件（如写使能有效），数据才会被写入目标位置。

    integer i;
    // 低电平有效复位 (Active-Low Reset)
    always @(posedge clk or negedge rst_n) begin
        if(!rst_n) begin
            // 复位时将所有寄存器清零
            for(i = 0; i < 32; i = i + 1) begin
                register_bank[i] <= 32'b0;
            end    
        end else if(write_enable && write_addr != 5'b0) begin
            // 写使能有效且不是写$zero寄存器时，写入数据
            register_bank[write_addr] <= write_data;
        end
    end

endmodule

cpp/verilog/Work/CPU_Project/testbench/unit_tests/register_file_tb.v
`timescale 1ns/1ps

module register_file_tb;

    // 测试信号
    reg clk;
    reg rst_n;
    reg write_enable;
    reg [4:0] read_addr1;
    reg [4:0] read_addr2;
    reg [4:0] write_addr;
    reg [31:0] write_data;
    wire [31:0] read_data1;
    wire [31:0] read_data2;
    
    // 实例化被测模块
    register_file uut (
        .clk(clk),
        .rst_n(rst_n),
        .write_enable(write_enable),
        .read_addr1(read_addr1),
        .read_addr2(read_addr2),
        .write_addr(write_addr),
        .write_data(write_data),
        .read_data1(read_data1),
        .read_data2(read_data2)
    );
    
    // 时钟生成
    always #5 clk = ~clk;
    
    // 测试过程
    initial begin
        // 初始化信号
        clk = 0;
        rst_n = 0;
        write_enable = 0;
        read_addr1 = 0;
        read_addr2 = 0;
        write_addr = 0;
        write_data = 0;
        
        // 波形记录
        $dumpfile("register_file_tb.vcd");
        $dumpvars(0, register_file_tb);
        
        // 测试1: 复位测试
        #10;
        rst_n = 1;
        #10;
        
        // 测试2: 读取$zero寄存器
        read_addr1 = 5'b0;
        #10;
        if (read_data1 !== 32'b0) 
            $display("Error: $zero register read value is not zero");
        else
            $display("Test passed: $zero register read value is zero");
        
        // 测试3: 写入和读取寄存器
        write_enable = 1;
        write_addr = 5'b1;     // 写入$at寄存器
        write_data = 32'h12345678;
        #10;
        
        read_addr1 = 5'b1;     // 读取$at寄存器
        #5;
        if (read_data1 !== 32'h12345678)
            $display("Error: Register write and read values do not match");
        else
            $display("Test passed: Register write and read values match");
        
        // 测试4: 同时读取两个寄存器
        write_addr = 5'b10;    // 写入$v0寄存器
        write_data = 32'habcdef12;
        #10;
        
        read_addr1 = 5'b1;     // 读取$at寄存器
        read_addr2 = 5'b10;    // 读取$v0寄存器
        #5;
        if (read_data1 !== 32'h12345678 || read_data2 !== 32'habcdef12)
            $display("Error: Dual-port read values do not match");
        else
            $display("Test passed: Dual-port read values match");
        
        // 测试5: 尝试写入$zero寄存器
        write_addr = 5'b0;     // 尝试写入$zero寄存器
        write_data = 32'hffffffff;
        #10;
        
        read_addr1 = 5'b0;     // 读取$zero寄存器
        #5;
        if (read_data1 !== 32'b0)
            $display("Error: $zero register was written to");
        else
            $display("Test passed: $zero register remains zero");
        
        // 测试6: 写使能无效时不应写入
        write_enable = 0;
        write_addr = 5'b11;    // 尝试写入$v1寄存器
        write_data = 32'hdeadbeef;
        #10;
        
        read_addr1 = 5'b11;    // 读取$v1寄存器
        #5;
        if (read_data1 !== 32'b0)
            $display("Error: Register written when write enable is disabled");
        else
            $display("Test passed: Register not written when write enable is disabled");
        
        // 测试7: 异步读取测试
        write_enable = 1;
        write_addr = 5'b100;   // 写入$a0寄存器
        write_data = 32'h11111111;
        #5; // 等待半个时钟周期
        
        // 在时钟上升沿之前检查读取是否立即生效
        read_addr1 = 5'b100;
        #1;
        if (read_data1 !== 32'h11111111)
            $display("Error: Asynchronous read did not take effect immediately");
        else
            $display("Test passed: Asynchronous read took effect immediately");
        
        #4; // 完成时钟周期
        
        // 完成测试
        #10;
        $display("All tests complete");
        $finish;
    end

endmodule

cpp/verilog/Work/CPU_Project/CPU_Project.sim/sim_1/behav/xsim/register_file_tb.vcd
$date
   Wed Sep 10 11:29:26 2025
$end

$version
  2025.1.0
  $dumpfile ("register_file_tb.vcd") 
$end

$timescale
  1ps
$end

$scope module register_file_tb $end
$var reg 1 ! clk $end
$var reg 1 " rst_n $end
$var reg 1 # write_enable $end
$var reg 5 $ read_addr1 [4:0] $end
$var reg 5 % read_addr2 [4:0] $end
$var reg 5 & write_addr [4:0] $end
$var reg 32 ' write_data [31:0] $end
$var wire 32 ( read_data1 [31:0] $end
$var wire 32 ) read_data2 [31:0] $end
$scope module uut $end
$var wire 1 * clk $end
$var wire 1 + rst_n $end
$var wire 1 , write_enable $end
$var wire 5 - read_addr1 [4:0] $end
$var wire 5 . read_addr2 [4:0] $end
$var wire 5 / write_addr [4:0] $end
$var wire 32 0 write_data [31:0] $end
$var wire 32 ( read_data1 [31:0] $end
$var wire 32 ) read_data2 [31:0] $end
$var integer 32 1 i [31:0] $end
$upscope $end
$upscope $end
$enddefinitions $end

#0
$dumpvars
0!
0"
0#
b0 $
b0 %
b0 &
b0 '
b0 (
b0 )
0*
0+
0,
b0 -
b0 .
b0 /
b0 0
bx 1
$end

#5000
1!
1*

#10000
0!
1"
0*
1+

#15000
1!
1*

#20000
0!
0*

#25000
1!
1*

#30000
0!
1#
b1 &
b10010001101000101011001111000 '
0*
1,
b1 /
b10010001101000101011001111000 0

#35000
1!
1*

#40000
0!
b1 $
b10010001101000101011001111000 (
0*
b1 -

#45000
1!
b10 &
b10101011110011011110111100010010 '
1*
b10 /
b10101011110011011110111100010010 0

#50000
0!
0*

#55000
1!
b10 %
b10101011110011011110111100010010 )
1*
b10 .

#60000
0!
b0 &
b11111111111111111111111111111111 '
0*
b0 /
b11111111111111111111111111111111 0

#65000
1!
1*

#70000
0!
b0 $
b0 (
0*
b0 -

#75000
1!
0#
b11 &
b11011110101011011011111011101111 '
1*
0,
b11 /
b11011110101011011011111011101111 0

#80000
0!
0*

#85000
1!
b11 $
1*
b11 -

#90000
0!
1#
b100 &
b10001000100010001000100010001 '
0*
1,
b100 /
b10001000100010001000100010001 0

#95000
1!
b100 $
b10001000100010001000100010001 (
1*
b100 -

