cpp/verilog/Work/Multi_Digit_IP_old/直接调用IPN的代码/muxN_bin.v
module muxN_bin #(parameter N = 8)(
    input wire [N-1:0] A, B,
    input wire Sel,
    output wire [N-1:0] Y
);

    assign Y = Sel ? B : A;

endmodule

cpp/verilog/Work/Multi_Digit_IP_old/sim/muxN_bin_tb.v
`timescale 1ns/1ps

module muxN_bin_tb;
    // 测试参数
    parameter N = 8;
    parameter TEST_COUNT = 10;
    parameter CLK_PERIOD = 10;
    
    // 测试信号
    reg [N-1:0] A, B;
    reg Sel;
    wire [N-1:0] Y;
    
    // 时钟生成（用于随机测试）
    reg clk;
    always #(CLK_PERIOD/2) clk = ~clk;
    
    // 实例化被测设计
    muxN_bin #(.N(N)) uut (
        .A(A),
        .B(B),
        .Sel(Sel),
        .Y(Y)
    );
    
    // 测试过程
    initial begin
        // 初始化
        clk = 0;
        A = 0;
        B = 0;
        Sel = 0;
        
        // 测试1: Sel=0时选择A
        $display("Test 1: Sel=0, should output A");
        A = 8'b10101010;
        B = 8'b01010101;
        Sel = 0;
        #20;
        if (Y !== A) 
            $display("ERROR: Expected %b, Got %b", A, Y);
        else
            $display("PASS: Output matches A");
        
        // 测试2: Sel=1时选择B
        $display("Test 2: Sel=1, should output B");
        Sel = 1;
        #20;
        if (Y !== B) 
            $display("ERROR: Expected %b, Got %b", B, Y);
        else
            $display("PASS: Output matches B");
        
        // 测试3: 随机测试
        $display("Test 3: Random tests");
        for (integer i = 0; i < TEST_COUNT; i = i + 1) begin
            A = $random;
            B = $random;
            Sel = $random % 2;
            #20;
            
            if ((Sel === 0 && Y !== A) || (Sel === 1 && Y !== B))
                $display("ERROR: Test %0d failed. Sel=%b, A=%b, B=%b, Y=%b", 
                         i, Sel, A, B, Y);
            else
                $display("PASS: Test %0d", i);
        end
        
        // 测试完成
        $display("All tests completed");
        $finish;
    end
    
    // 波形记录
    initial begin
        $dumpfile("muxN_bin.vcd");
        $dumpvars(0, muxN_bin_tb);
    end
endmodule

cpp/verilog/Work/Multi_Digit_IP_old/Multi_Digit_IP.sim/sim_1/behav/xsim/muxN_bin.vcd
$date
   Mon Sep  8 14:29:30 2025
$end

$version
  2025.1.0
  $dumpfile ("muxN_bin.vcd") 
$end

$timescale
  1ps
$end

$scope module muxN_bin_tb $end
$var reg 8 ! A [7:0] $end
$var reg 8 " B [7:0] $end
$var reg 1 # Sel $end
$var wire 8 $ Y [7:0] $end
$var reg 1 % clk $end
$scope module uut $end
$var wire 8 & A [7:0] $end
$var wire 8 ' B [7:0] $end
$var wire 1 ( Sel $end
$var wire 8 $ Y [7:0] $end
$scope module mux_loop[0].mux2 $end
$var wire 2 ) A [1:0] $end
$var wire 2 * B [1:0] $end
$var wire 1 ( Sel $end
$var wire 2 + Y [1:0] $end
$upscope $end
$scope module mux_loop[1].mux2 $end
$var wire 2 , A [3:2] $end
$var wire 2 - B [3:2] $end
$var wire 1 ( Sel $end
$var wire 2 . Y [3:2] $end
$upscope $end
$scope module mux_loop[2].mux2 $end
$var wire 2 / A [5:4] $end
$var wire 2 0 B [5:4] $end
$var wire 1 ( Sel $end
$var wire 2 1 Y [5:4] $end
$upscope $end
$scope module mux_loop[3].mux2 $end
$var wire 2 2 A [7:6] $end
$var wire 2 3 B [7:6] $end
$var wire 1 ( Sel $end
$var wire 2 4 Y [7:6] $end
$upscope $end
$upscope $end
$scope begin Block56_2 $end
$var integer 32 5 i [31:0] $end
$upscope $end
$upscope $end
$enddefinitions $end

#0
$dumpvars
b10101010 !
b1010101 "
0#
b10101010 $
0%
b10101010 &
b1010101 '
0(
b10 )
b1 *
b10 +
b10 ,
b1 -
b10 .
b10 /
b1 0
b10 1
b10 2
b1 3
b10 4
bx 5
$end

#5000
1%

#10000
0%

#15000
1%

#20000
1#
b1010101 $
0%
1(
b1 +
b1 .
b1 1
b1 4

#25000
1%

#30000
0%

#35000
1%

#40000
b100100 !
b10000001 "
b10000001 $
0%
b100100 &
b10000001 '
b0 )
b1 *
b1 ,
b0 -
b0 .
b10 /
b0 0
b0 1
b0 2
b10 3
b10 4
b0 5

#45000
1%

#50000
0%

#55000
1%

#60000
b1100011 !
b1101 "
b1101 $
0%
b1100011 &
b1101 '
b11 )
b1 *
b0 ,
b11 -
b11 .
b10 /
b0 0
b1 2
b0 3
b0 4
b1 5

#65000
1%

#70000
0%

#75000
1%

#80000
b1100101 !
b10010 "
b10010 $
0%
b1100101 &
b10010 '
b1 )
b10 *
b10 +
b1 ,
b0 -
b0 .
b10 /
b1 0
b1 1
b1 2
b0 3
b10 5

#85000
1%

#90000
0%

#95000
1%

#100000
b1101 !
b1110110 "
b1110110 $
0%
b1101 &
b1110110 '
b1 )
b10 *
b11 ,
b1 -
b1 .
b0 /
b11 0
b11 1
b0 2
b1 3
b1 4
b11 5

#105000
1%

#110000
0%

#115000
1%

#120000
b11101101 !
b10001100 "
b10001100 $
0%
b11101101 &
b10001100 '
b1 )
b0 *
b0 +
b11 ,
b11 -
b11 .
b10 /
b0 0
b0 1
b11 2
b10 3
b10 4
b100 5

#125000
1%

#130000
0%

#135000
1%

#140000
b11000110 !
b11000101 "
0#
b11000110 $
0%
b11000110 &
b11000101 '
0(
b10 )
b1 *
b10 +
b1 ,
b1 -
b1 .
b0 /
b0 0
b11 2
b11 3
b11 4
b101 5

#145000
1%

#150000
0%

#155000
1%

#160000
b11100101 !
b1110111 "
b11100101 $
0%
b11100101 &
b1110111 '
b1 )
b11 *
b1 +
b1 ,
b1 -
b10 /
b11 0
b10 1
b11 2
b1 3
b110 5

#165000
1%

#170000
0%

#175000
1%

#180000
b10001111 !
b11110010 "
b10001111 $
0%
b10001111 &
b11110010 '
b11 )
b10 *
b11 +
b11 ,
b0 -
b11 .
b0 /
b11 0
b0 1
b10 2
b11 3
b10 4
b111 5

#185000
1%

#190000
0%

#195000
1%

#200000
b11101000 !
b11000101 "
b11101000 $
0%
b11101000 &
b11000101 '
b0 )
b1 *
b0 +
b10 ,
b1 -
b10 .
b10 /
b0 0
b10 1
b11 2
b11 3
b11 4
b1000 5

#205000
1%

#210000
0%

#215000
1%

#220000
b10111101 !
b101101 "
1#
b101101 $
0%
b10111101 &
b101101 '
1(
b1 )
b1 *
b1 +
b11 ,
b11 -
b11 .
b11 /
b10 0
b10 2
b0 3
b0 4
b1001 5

#225000
1%

#230000
0%

#235000
1%

#240000
b1010 5
